simple_star_patterns/__init__.py
simple_star_patterns/simple_stars.py
simple_star_patterns-0.2.3.dist-info/METADATA
simple_star_patterns-0.2.3.dist-info/WHEEL
simple_star_patterns-0.2.3.dist-info/top_level.txt
simple_star_patterns-0.2.3.dist-info/RECORD
