Metadata-Version: 2.2
Name: simple_star_patterns
Version: 0.2.3
Summary: A simple library for printing star patterns
Author: Yash Agrawal
Author-email: yashmtr1744@gmail.com
Classifier: Programming Language :: Python :: 3
Classifier: License :: OSI Approved :: MIT License
Classifier: Operating System :: OS Independent
Requires-Python: >=3.6
Dynamic: author
Dynamic: author-email
Dynamic: classifier
Dynamic: description
Dynamic: description-content-type
Dynamic: requires-python
Dynamic: summary
